Topsis_Rupam_102317201/__init__.py
Topsis_Rupam_102317201/topsis.py
topsis_rupam_102317201-0.0.3.dist-info/METADATA
topsis_rupam_102317201-0.0.3.dist-info/WHEEL
topsis_rupam_102317201-0.0.3.dist-info/entry_points.txt
topsis_rupam_102317201-0.0.3.dist-info/top_level.txt
topsis_rupam_102317201-0.0.3.dist-info/RECORD
