Metadata-Version: 2.4
Name: Topsis_Rupam_102317201
Version: 0.0.3
Summary: Python pkg for TOPSIS method for MCMD problems 
Home-page: https://github.com/ProfessionalYapper0311
Author: Rupam
Author-email: rbiswas_be23@thapar.edu
Keywords: python,topsis,topsis-rupam,topsis-rupam-102317201
Classifier: Programming Language :: Python :: 3
Classifier: License :: OSI Approved :: MIT License
Classifier: Operating System :: OS Independent
Requires-Dist: pandas
Requires-Dist: numpy
Dynamic: author
Dynamic: author-email
Dynamic: classifier
Dynamic: description
Dynamic: description-content-type
Dynamic: home-page
Dynamic: keywords
Dynamic: requires-dist
Dynamic: summary
